topsis_harsaihaj/__init__.py
topsis_harsaihaj/topsis.py
topsis_harsaihaj_123456-1.0.6.dist-info/licenses/LICENSE
topsis_harsaihaj_123456-1.0.6.dist-info/METADATA
topsis_harsaihaj_123456-1.0.6.dist-info/WHEEL
topsis_harsaihaj_123456-1.0.6.dist-info/entry_points.txt
topsis_harsaihaj_123456-1.0.6.dist-info/top_level.txt
topsis_harsaihaj_123456-1.0.6.dist-info/RECORD
