Metadata-Version: 2.4
Name: Topsis-Harsaihaj-123456
Version: 1.0.6
Summary: TOPSIS package for Multi-Criteria Decision Making
Author: Harsaihaj Singh
Author-email: harsaihaj@example.com
Classifier: Programming Language :: Python :: 3
Classifier: License :: OSI Approved :: MIT License
Classifier: Operating System :: OS Independent
Requires-Python: >=3.6
License-File: LICENSE
Dynamic: author
Dynamic: author-email
Dynamic: classifier
Dynamic: description
Dynamic: description-content-type
Dynamic: license-file
Dynamic: requires-python
Dynamic: summary
